{
    "ht": "ICreole yaseHaiti",
    "sa": "ISanskrit",
    "sq": "Isi-Albania",
    "am": "Isi-Amharic",
    "ar": "Isi-Arabic",
    "hy": "Isi-Armenian",
    "ay": "Isi-Aymara",
    "az": "Isi-Azerbaijani",
    "bm": "Isi-Bambara",
    "be": "Isi-Belarusian",
    "bs": "Isi-Bosnia",
    "hr": "Isi-Croatia",
    "cs": "Isi-Czech",
    "da": "Isi-Danish",
    "eo": "Isi-Esperanto",
    "et": "Isi-Estonian",
    "ee": "Isi-Ewe",
    "fi": "Isi-Finnish",
    "fy": "Isi-Frisian",
    "gu": "Isi-Gujarati",
    "hu": "Isi-Hungarian",
    "is": "Isi-Icelandic",
    "ig": "Isi-Igbo",
    "ilo": "Isi-Iloko",
    "id": "Isi-Indonesian",
    "ga": "Isi-Irish",
    "it": "Isi-Italian",
    "ko": "Isi-Korean",
    "kri": "Isi-Krio",
    "ku": "Isi-Kurdish (isi-Kurmanji)",
    "ckb": "Isi-Kurdish (isi-Sorani)",
    "lt": "Isi-Lithuanian",
    "lg": "Isi-Luganda",
    "mai": "Isi-Maithili",
    "ms": "Isi-Malay",
    "lus": "Isi-Mizo",
    "no": "Isi-Norwegian",
    "or": "Isi-Odia (Oriya)",
    "om": "Isi-Oromo",
    "fa": "Isi-Persia",
    "pl": "Isi-Polish",
    "qu": "Isi-Quechua",
    "ro": "Isi-Romanian",
    "ru": "Isi-Russian",
    "sr": "Isi-Serbia",
    "sk": "Isi-Slovak",
    "sl": "Isi-Slovenian",
    "es": "Isi-Spanish",
    "sv": "Isi-Swedish",
    "ti": "Isi-Tigrinya",
    "uk": "Isi-Ukranian",
    "ur": "Isi-Urdu",
    "ug": "Isi-Uyghur",
    "uz": "Isi-Uzbek",
    "as": "isiAssamese",
    "eu": "IsiBasque",
    "bn": "IsiBengali",
    "bho": "IsiBhojpuri",
    "af": "Isibhulu",
    "bg": "IsiBulgaria",
    "my": "IsiBurmese",
    "km": "isiCambodia",
    "ca": "IsiCatalan",
    "ceb": "IsiCebuano",
    "ny": "IsiChichewa",
    "co": "IsiCorsican",
    "nl": "IsiDatshi",
    "dv": "IsiDivehi",
    "doi": "IsiDogri",
    "tl": "IsiFilipino",
    "fil": "IsiFilipino",
    "fr": "IsiFrentshi",
    "gl": "IsiGalician",
    "ka": "IsiGeorgia",
    "el": "IsiGreek",
    "gn": "IsiGuarani",
    "ha": "IsiHausa",
    "haw": "IsiHawayi",
    "iw": "IsiHebhere",
    "he": "IsiHebhere",
    "hi": "IsiHindi",
    "hmn": "IsiHmong",
    "de": "IsiJamani",
    "ja": "IsiJapanese",
    "jw": "IsiJavanese",
    "jv": "IsiJavanese",
    "kn": "IsiKannada",
    "kk": "IsiKazakh",
    "rw": "IsiKinyarwanda",
    "gom": "IsiKonkani",
    "lo": "IsiLao",
    "la": "IsiLatin",
    "lv": "IsiLatvian",
    "ln": "IsiLingala",
    "lb": "IsiLuxembourgish",
    "mk": "IsiMacedenian",
    "mg": "IsiMalagasy",
    "ml": "IsiMalayalam",
    "mt": "IsiMaltese",
    "mi": "IsiMaori",
    "mr": "IsiMarathi",
    "mni-Mtei": "IsiMeiteilon (Manipuri)",
    "mn": "IsiMongolian",
    "ne": "IsiNepali",
    "en": "IsiNgesi",
    "ps": "IsiPashto",
    "nso": "isiPedi",
    "pt": "IsiPhuthukezi",
    "pa": "IsiPunjabi",
    "sm": "IsiSamoan",
    "gd": "IsiScots Gaelic",
    "sn": "IsiShona",
    "sd": "isiSindhi",
    "si": "IsiSinhala",
    "so": "IsiSomaliya",
    "su": "IsiSudanese",
    "st": "IsiSuthu",
    "sw": "IsiSwahili",
    "tg": "IsiTajik",
    "ta": "IsiTamil",
    "tt": "IsiTatar",
    "te": "IsiTelugu",
    "th": "IsiThai",
    "zh": "IsiTshayina (Esenziwe lula)",
    "zh-CN": "IsiTshayina (Esenziwe lula)",
    "zh-TW": "IsiTshayina (Esiqhelekileyo)",
    "ts": "IsiTsonga",
    "tr": "IsiTurkish",
    "tk": "IsiTurkmen",
    "ak": "IsiTwi",
    "vi": "IsiVietnamese",
    "cy": "IsiWelsh",
    "xh": "IsiXhosa",
    "yi": "IsiYiddish",
    "yo": "IsiYoruba",
    "zu": "IsiZulu",
    "ky": "Kyrgyz"
}